[
    {
        "name": "id",
        "dbType": "increments",
        "htmlType": null,
        "validations": null,
        "searchable": false,
        "fillable": false,
        "primary": true,
        "inForm": false,
        "inIndex": false
    },
    {
        "name": "post_id",
        "dbType": "Integer",
        "htmlType": null,
        "validations": "required",
        "searchable": true,
        "fillable": true,
        "primary": false,
        "inForm": true,
        "inIndex": true
    },
    {
        "name": "comment_id",
        "dbType": "Integer",
        "htmlType": null,
        "validations": "required",
        "searchable": true,
        "fillable": true,
        "primary": false,
        "inForm": true,
        "inIndex": true
    },
    {
        "name": "read",
        "dbType": "Boolean",
        "htmlType": null,
        "validations": "required",
        "searchable": true,
        "fillable": true,
        "primary": false,
        "inForm": true,
        "inIndex": true
    },
    {
        "name": "new_comment",
        "dbType": "Boolean",
        "htmlType": null,
        "validations": "",
        "searchable": true,
        "fillable": true,
        "primary": false,
        "inForm": true,
        "inIndex": true
    },
    {
        "name": "phone_number",
        "dbType": "string",
        "htmlType": "255",
        "validations": "",
        "searchable": true,
        "fillable": true,
        "primary": false,
        "inForm": true,
        "inIndex": true
    },
    {
        "name": "created_at",
        "dbType": "timestamp",
        "htmlType": null,
        "validations": null,
        "searchable": false,
        "fillable": false,
        "primary": false,
        "inForm": false,
        "inIndex": false
    },
    {
        "name": "updated_at",
        "dbType": "timestamp",
        "htmlType": null,
        "validations": null,
        "searchable": false,
        "fillable": false,
        "primary": false,
        "inForm": false,
        "inIndex": false
    }
]